sushi_batch/__init__.py
sushi_batch/__main__.py
sushi_batch/console_utils.py
sushi_batch/enums.py
sushi_batch/file_dialogs.py
sushi_batch/files.py
sushi_batch/job.py
sushi_batch/job_queue.py
sushi_batch/json_hooks.py
sushi_batch/mkv_merge.py
sushi_batch/queue_manager.py
sushi_batch/settings.py
sushi_batch/streams.py
sushi_batch/sub_sync.py
sushi_batch-0.1.0.dist-info/entry_points.txt
sushi_batch-0.1.0.dist-info/LICENSE
sushi_batch-0.1.0.dist-info/METADATA
sushi_batch-0.1.0.dist-info/WHEEL
sushi_batch-0.1.0.dist-info/RECORD
