Metadata-Version: 2.1
Name: sushi-batch
Version: 0.1.0
Summary: Batch Subtitle Synchronization Tool
Home-page: https://github.com/C1fer/sushi-batch
License: MIT
Keywords: subtitle,sync
Author: C1fer
Requires-Python: >=3.10,<4.0
Classifier: Development Status :: 5 - Production/Stable
Classifier: License :: OSI Approved :: MIT License
Classifier: Programming Language :: Python :: 3
Classifier: Programming Language :: Python :: 3.10
Classifier: Programming Language :: Python :: 3.11
Classifier: Topic :: Multimedia :: Sound/Audio
Classifier: Topic :: Text Processing
Requires-Dist: art (>=6.1,<7.0)
Requires-Dist: colorama (>=0.4.6,<0.5.0)
Requires-Dist: opencv-python (>=4.8.1.78,<5.0.0.0)
Requires-Dist: prettytable (>=3.9.0,<4.0.0)
Requires-Dist: pyqt6 (>=6.5.2,<7.0.0)
Requires-Dist: sushi-sub (>=0.6.2,<0.7.0)
Requires-Dist: yaspin (>=3.0.1,<4.0.0)
Project-URL: Repository, https://github.com/C1fer/sushi-batch
